ErioonDB/Test.py
ErioonDB/User.py
ErioonDB/__init__.py
ErioonDB/auth.py
ErioonDB/client.py
ErioonDB/collection.py
ErioonDB/database.py
ErioonDB/locks.py
ErioonDB/storage.py
ErioonDB-0.1.2.8.dist-info/LICENSE
ErioonDB-0.1.2.8.dist-info/METADATA
ErioonDB-0.1.2.8.dist-info/WHEEL
ErioonDB-0.1.2.8.dist-info/top_level.txt
ErioonDB-0.1.2.8.dist-info/RECORD
