Metadata-Version: 2.2
Name: ErioonDB
Version: 0.1.2.8
Summary: ErioonDB Engine
Author: Erioon
Author-email: hello@erioon.com
Classifier: Programming Language :: Python :: 3
Classifier: License :: OSI Approved :: MIT License
Classifier: Operating System :: OS Independent
Requires-Python: >=3.6
License-File: LICENSE
Dynamic: author
Dynamic: author-email
Dynamic: classifier
Dynamic: requires-python
Dynamic: summary
